Metadata-Version: 2.1
Name: alf-auth0
Version: 0.8.1
Summary: OAuth Client adapted to work with Auth0
Home-page: https://github.com/globocom/alf
Author: Globo.com
Author-email: timecore@corp.globo.com
License: MIT
Keywords: oauth client client_credentials requests auth0
Platform: UNKNOWN
Classifier: Intended Audience :: Developers
Classifier: License :: OSI Approved :: MIT License
Classifier: Programming Language :: Python :: 2.7
Classifier: Programming Language :: Python :: 3
Classifier: Programming Language :: Python :: 3.3
Requires-Dist: requests (>=1.2.3)
